{
  "db_name": "PostgreSQL",
  "query": "SELECT MAX(dt_ref)                                            AS \"data_ref?\",\n                  COUNT(*)                                               AS \"total!\",\n                  COALESCE(SUM(qtd_sugerida), 0)::bigint                 AS \"sugerido!\",\n                  AVG(cobertura_dias) FILTER (WHERE cobertura_dias <> $1) AS \"cobertura?\"\n           FROM pcp.produto_ativo",
  "describe": {
    "columns": [
      {
        "ordinal": 0,
        "name": "data_ref?",
        "type_info": "Date",
        "origin": "Expression"
      },
      {
        "ordinal": 1,
        "name": "total!",
        "type_info": "Int8",
        "origin": "Expression"
      },
      {
        "ordinal": 2,
        "name": "sugerido!",
        "type_info": "Int8",
        "origin": "Expression"
      },
      {
        "ordinal": 3,
        "name": "cobertura?",
        "type_info": "Float8",
        "origin": "Expression"
      }
    ],
    "parameters": {
      "Left": [
        "Float8"
      ]
    },
    "nullable": [
      null,
      null,
      null,
      null
    ]
  },
  "hash": "56ef55eb4551bc9b592ad724843ac3d568399d884c54878aa27734eb4b3e3b63"
}
